[{"date": "20191111", "reseller-id": 1002, "productName": "4.25x6 Greetings from Riga", "qty": 6, "totalAmount": 16.200000000000003, "salesChannel": "web", "customer": {"firstname": "Reginald", "lastname": "Quinney", "email": "Reginald.Quinney@example.com"}, "dateCreated": "20191111", "seriesCity": "Riga", "Created Date": "2019-11-11", "transactionId": 20410}, {"date": "20191111", "reseller-id": 1002, "productName": "6x9 Come visit me in Valencia", "qty": 5, "totalAmount": 12.0, "salesChannel": "web", "customer": {"firstname": "Marilyn", "lastname": "Berry", "email": "Marilyn.Berry@example.com"}, "dateCreated": "20191111", "seriesCity": "Valencia", "Created Date": "2019-11-11", "transactionId": 20411}, {"date": "20191111", "reseller-id": 1002, "productName": "6x9 Greetings from Kishinev", "qty": 3, "totalAmount": 9.3, "salesChannel": "in-store", "customer": {"firstname": "Thomas", "lastname": "Blake", "email": "Thomas.Blake@example.com"}, "dateCreated": "20191111", "seriesCity": "Kishinev", "Created Date": "2019-11-11", "transactionId": 20412}, {"date": "20191111", "reseller-id": 1002, "productName": "4.25x6 Greetings from Kiev", "qty": 4, "totalAmount": 9.2, "salesChannel": "web", "customer": {"firstname": "Anna", "lastname": "Allen", "email": "Anna.Allen@example.com"}, "dateCreated": "20191111", "seriesCity": "Kiev", "Created Date": "2019-11-11", "transactionId": 20413}, {"date": "20191111", "reseller-id": 1002, "productName": "4x6 Come visit me in Lipetsk", "qty": 3, "totalAmount": 4.800000000000001, "salesChannel": "mobile app", "customer": {"firstname": "Ryan", "lastname": "Colburn", "email": "Ryan.Colburn@example.com"}, "dateCreated": "20191111", "seriesCity": "Lipetsk", "Created Date": "2019-11-11", "transactionId": 20414}, {"date": "20191111", "reseller-id": 1002, "productName": "5x7 All the love from Kobenhavn (Copenhagen)", "qty": 2, "totalAmount": 5.4, "salesChannel": "web", "customer": {"firstname": "Jeffery", "lastname": "Coco", "email": "Jeffery.Coco@example.com"}, "dateCreated": "20191111", "seriesCity": "Kobenhavn (Copenhagen)", "Created Date": "2019-11-11", "transactionId": 20415}, {"date": "20191111", "reseller-id": 1002, "productName": "6x11 Just settled in Valencia", "qty": 2, "totalAmount": 6.6, "salesChannel": "mobile app", "customer": {"firstname": "Maria", "lastname": "Grissom", "email": "Maria.Grissom@example.com"}, "dateCreated": "20191111", "seriesCity": "Valencia", "Created Date": "2019-11-11", "transactionId": 20416}, {"date": "20191111", "reseller-id": 1002, "productName": "4x6 Just settled in Helsinki", "qty": 4, "totalAmount": 7.6, "salesChannel": "mobile app", "customer": {"firstname": "Mary", "lastname": "Maness", "email": "Mary.Maness@example.com"}, "dateCreated": "20191111", "seriesCity": "Helsinki", "Created Date": "2019-11-11", "transactionId": 20417}, {"date": "20191111", "reseller-id": 1002, "productName": "6x9 Merry Christmas from Leeds", "qty": 4, "totalAmount": 6.4, "salesChannel": "web", "customer": {"firstname": "David", "lastname": "Thomas", "email": "David.Thomas@example.com"}, "dateCreated": "20191111", "seriesCity": "Leeds", "Created Date": "2019-11-11", "transactionId": 20418}, {"date": "20191111", "reseller-id": 1002, "productName": "6x11 Just settled in Zagreb", "qty": 2, "totalAmount": 4.0, "salesChannel": "mobile app", "customer": {"firstname": "Evelyn", "lastname": "Richardson", "email": "Evelyn.Richardson@example.com"}, "dateCreated": "20191111", "seriesCity": "Zagreb", "Created Date": "2019-11-11", "transactionId": 20419}, {"date": "20191111", "reseller-id": 1002, "productName": "6x11 Come visit me in Kishinev", "qty": 5, "totalAmount": 10.0, "salesChannel": "mobile app", "customer": {"firstname": "Robert", "lastname": "Seanez", "email": "Robert.Seanez@example.com"}, "dateCreated": "20191111", "seriesCity": "Kishinev", "Created Date": "2019-11-11", "transactionId": 20420}, {"date": "20191111", "reseller-id": 1002, "productName": "4x6 Merry Christmas from Kiev", "qty": 1, "totalAmount": 1.6, "salesChannel": "web", "customer": {"firstname": "Ethel", "lastname": "Trahan", "email": "Ethel.Trahan@example.com"}, "dateCreated": "20191111", "seriesCity": "Kiev", "Created Date": "2019-11-11", "transactionId": 20421}, {"date": "20191111", "reseller-id": 1002, "productName": "4x6 All the love from Orenburg", "qty": 2, "totalAmount": 5.4, "salesChannel": "web", "customer": {"firstname": "James", "lastname": "Puckett", "email": "James.Puckett@example.com"}, "dateCreated": "20191111", "seriesCity": "Orenburg", "Created Date": "2019-11-11", "transactionId": 20422}, {"date": "20191111", "reseller-id": 1002, "productName": "5.5x8.5 Merry Christmas from Odessa", "qty": 5, "totalAmount": 20.0, "salesChannel": "web", "customer": {"firstname": "Zenaida", "lastname": "Cook", "email": "Zenaida.Cook@example.com"}, "dateCreated": "20191111", "seriesCity": "Odessa", "Created Date": "2019-11-11", "transactionId": 20423}, {"date": "20191111", "reseller-id": 1002, "productName": "5x7 Greetings from Krasnoyarsk", "qty": 1, "totalAmount": 2.7, "salesChannel": "web", "customer": {"firstname": "Numbers", "lastname": "Mcalpin", "email": "Numbers.Mcalpin@example.com"}, "dateCreated": "20191111", "seriesCity": "Krasnoyarsk", "Created Date": "2019-11-11", "transactionId": 20424}, {"date": "20191111", "reseller-id": 1002, "productName": "4x6 All the love from K\u00f6ln (Cologne)", "qty": 5, "totalAmount": 17.5, "salesChannel": "web", "customer": {"firstname": "Michael", "lastname": "Tsan", "email": "Michael.Tsan@example.com"}, "dateCreated": "20191111", "seriesCity": "K\u00f6ln (Cologne)", "Created Date": "2019-11-11", "transactionId": 20425}, {"date": "20191111", "reseller-id": 1002, "productName": "5x7 Merry Christmas from Kemerovo", "qty": 6, "totalAmount": 22.200000000000003, "salesChannel": "web", "customer": {"firstname": "Hector", "lastname": "Blake", "email": "Hector.Blake@example.com"}, "dateCreated": "20191111", "seriesCity": "Kemerovo", "Created Date": "2019-11-11", "transactionId": 20426}, {"date": "20191111", "reseller-id": 1002, "productName": "5.5x8.5 All the love from Donetsk ", "qty": 3, "totalAmount": 5.699999999999999, "salesChannel": "mobile app", "customer": {"firstname": "Angela", "lastname": "Colburn", "email": "Angela.Colburn@example.com"}, "dateCreated": "20191111", "seriesCity": "Donetsk ", "Created Date": "2019-11-11", "transactionId": 20427}, {"date": "20191111", "reseller-id": 1002, "productName": "5.5x8.5 Merry Christmas from Minsk", "qty": 2, "totalAmount": 7.4, "salesChannel": "mobile app", "customer": {"firstname": "Marilyn", "lastname": "Thal", "email": "Marilyn.Thal@example.com"}, "dateCreated": "20191111", "seriesCity": "Minsk", "Created Date": "2019-11-11", "transactionId": 20428}, {"date": "20191111", "reseller-id": 1002, "productName": "5.5x8.5 Greetings from Bremen", "qty": 5, "totalAmount": 21.5, "salesChannel": "web", "customer": {"firstname": "Hugo", "lastname": "Wenger", "email": "Hugo.Wenger@example.com"}, "dateCreated": "20191111", "seriesCity": "Bremen", "Created Date": "2019-11-11", "transactionId": 20429}, {"date": "20191111", "reseller-id": 1002, "productName": "4x6 Just settled in Omsk", "qty": 3, "totalAmount": 5.699999999999999, "salesChannel": "mobile app", "customer": {"firstname": "Rebekah", "lastname": "Hickman", "email": "Rebekah.Hickman@example.com"}, "dateCreated": "20191111", "seriesCity": "Omsk", "Created Date": "2019-11-11", "transactionId": 20430}, {"date": "20191111", "reseller-id": 1002, "productName": "5.5x8.5 Merry Christmas from D\u00fcsseldorf", "qty": 6, "totalAmount": 21.0, "salesChannel": "web", "customer": {"firstname": "Mark", "lastname": "Maugeri", "email": "Mark.Maugeri@example.com"}, "dateCreated": "20191111", "seriesCity": "D\u00fcsseldorf", "Created Date": "2019-11-11", "transactionId": 20431}, {"date": "20191111", "reseller-id": 1002, "productName": "5x7 Just settled in Tula", "qty": 3, "totalAmount": 7.199999999999999, "salesChannel": "web", "customer": {"firstname": "David", "lastname": "Legette", "email": "David.Legette@example.com"}, "dateCreated": "20191111", "seriesCity": "Tula", "Created Date": "2019-11-11", "transactionId": 20432}, {"date": "20191111", "reseller-id": 1002, "productName": "5.5x8.5 Greetings from Nizhny Novgorod", "qty": 1, "totalAmount": 2.5, "salesChannel": "in-store", "customer": {"firstname": "Christine", "lastname": "Howard", "email": "Christine.Howard@example.com"}, "dateCreated": "20191111", "seriesCity": "Nizhny Novgorod", "Created Date": "2019-11-11", "transactionId": 20433}, {"date": "20191111", "reseller-id": 1002, "productName": "6x11 Greetings from Yaroslave", "qty": 1, "totalAmount": 1.9, "salesChannel": "mobile app", "customer": {"firstname": "Sarah", "lastname": "Spears", "email": "Sarah.Spears@example.com"}, "dateCreated": "20191111", "seriesCity": "Yaroslave", "Created Date": "2019-11-11", "transactionId": 20434}, {"date": "20191111", "reseller-id": 1002, "productName": "6x11 Come visit me in Penza", "qty": 6, "totalAmount": 11.399999999999999, "salesChannel": "mobile app", "customer": {"firstname": "Sharlene", "lastname": "Westfield", "email": "Sharlene.Westfield@example.com"}, "dateCreated": "20191111", "seriesCity": "Penza", "Created Date": "2019-11-11", "transactionId": 20435}, {"date": "20191111", "reseller-id": 1002, "productName": "6x9 Come visit me in Orenburg", "qty": 4, "totalAmount": 16.4, "salesChannel": "web", "customer": {"firstname": "Toshia", "lastname": "Destina", "email": "Toshia.Destina@example.com"}, "dateCreated": "20191111", "seriesCity": "Orenburg", "Created Date": "2019-11-11", "transactionId": 20436}, {"date": "20191111", "reseller-id": 1002, "productName": "5.5x8.5 Greetings from Kishinev", "qty": 1, "totalAmount": 2.6, "salesChannel": "web", "customer": {"firstname": "Doris", "lastname": "Garcia", "email": "Doris.Garcia@example.com"}, "dateCreated": "20191111", "seriesCity": "Kishinev", "Created Date": "2019-11-11", "transactionId": 20437}, {"date": "20191111", "reseller-id": 1002, "productName": "6x11 Greetings from Glasgow", "qty": 6, "totalAmount": 12.0, "salesChannel": "web", "customer": {"firstname": "Carmen", "lastname": "Simonetti", "email": "Carmen.Simonetti@example.com"}, "dateCreated": "20191111", "seriesCity": "Glasgow", "Created Date": "2019-11-11", "transactionId": 20438}, {"date": "20191111", "reseller-id": 1002, "productName": "5x7 Just settled in Sheffield", "qty": 2, "totalAmount": 8.0, "salesChannel": "web", "customer": {"firstname": "Ricardo", "lastname": "Straka", "email": "Ricardo.Straka@example.com"}, "dateCreated": "20191111", "seriesCity": "Sheffield", "Created Date": "2019-11-11", "transactionId": 20439}, {"date": "20191111", "reseller-id": 1002, "productName": "4.25x6 Merry Christmas from Volgograd", "qty": 6, "totalAmount": 20.4, "salesChannel": "web", "customer": {"firstname": "Maria", "lastname": "Davis", "email": "Maria.Davis@example.com"}, "dateCreated": "20191111", "seriesCity": "Volgograd", "Created Date": "2019-11-11", "transactionId": 20440}, {"date": "20191111", "reseller-id": 1002, "productName": "4x6 Merry Christmas from Stuttgart", "qty": 5, "totalAmount": 15.5, "salesChannel": "mobile app", "customer": {"firstname": "Ronald", "lastname": "Hertler", "email": "Ronald.Hertler@example.com"}, "dateCreated": "20191111", "seriesCity": "Stuttgart", "Created Date": "2019-11-11", "transactionId": 20441}, {"date": "20191111", "reseller-id": 1002, "productName": "5x7 Just settled in Riga", "qty": 2, "totalAmount": 5.2, "salesChannel": "mobile app", "customer": {"firstname": "Elliot", "lastname": "Olivero", "email": "Elliot.Olivero@example.com"}, "dateCreated": "20191111", "seriesCity": "Riga", "Created Date": "2019-11-11", "transactionId": 20442}, {"date": "20191111", "reseller-id": 1002, "productName": "4.25x6 Greetings from Helsinki", "qty": 4, "totalAmount": 13.2, "salesChannel": "mobile app", "customer": {"firstname": "Kathleen", "lastname": "Thomas", "email": "Kathleen.Thomas@example.com"}, "dateCreated": "20191111", "seriesCity": "Helsinki", "Created Date": "2019-11-11", "transactionId": 20443}, {"date": "20191111", "reseller-id": 1002, "productName": "4x6 Merry Christmas from D\u00fcsseldorf", "qty": 6, "totalAmount": 19.799999999999997, "salesChannel": "web", "customer": {"firstname": "Chere", "lastname": "Bush", "email": "Chere.Bush@example.com"}, "dateCreated": "20191111", "seriesCity": "D\u00fcsseldorf", "Created Date": "2019-11-11", "transactionId": 20444}, {"date": "20191111", "reseller-id": 1002, "productName": "4x6 Come visit me in Sarajevo", "qty": 4, "totalAmount": 6.0, "salesChannel": "mobile app", "customer": {"firstname": "Toshia", "lastname": "Boothroyd", "email": "Toshia.Boothroyd@example.com"}, "dateCreated": "20191111", "seriesCity": "Sarajevo", "Created Date": "2019-11-11", "transactionId": 20445}, {"date": "20191111", "reseller-id": 1002, "productName": "4x6 Merry Christmas from Amsterdam", "qty": 3, "totalAmount": 10.2, "salesChannel": "mobile app", "customer": {"firstname": "Albert", "lastname": "Bay", "email": "Albert.Bay@example.com"}, "dateCreated": "20191111", "seriesCity": "Amsterdam", "Created Date": "2019-11-11", "transactionId": 20446}, {"date": "20191111", "reseller-id": 1002, "productName": "6x11 Come visit me in Volgograd", "qty": 5, "totalAmount": 20.5, "salesChannel": "mobile app", "customer": {"firstname": "Marjorie", "lastname": "Griffith", "email": "Marjorie.Griffith@example.com"}, "dateCreated": "20191111", "seriesCity": "Volgograd", "Created Date": "2019-11-11", "transactionId": 20447}, {"date": "20191111", "reseller-id": 1002, "productName": "5x7 Merry Christmas from Vladivostok", "qty": 3, "totalAmount": 7.5, "salesChannel": "mobile app", "customer": {"firstname": "Lenora", "lastname": "Tucker", "email": "Lenora.Tucker@example.com"}, "dateCreated": "20191111", "seriesCity": "Vladivostok", "Created Date": "2019-11-11", "transactionId": 20448}, {"date": "20191111", "reseller-id": 1002, "productName": "6x11 Merry Christmas from Essen", "qty": 4, "totalAmount": 10.4, "salesChannel": "web", "customer": {"firstname": "Manuel", "lastname": "Boothroyd", "email": "Manuel.Boothroyd@example.com"}, "dateCreated": "20191111", "seriesCity": "Essen", "Created Date": "2019-11-11", "transactionId": 20449}, {"date": "20191111", "reseller-id": 1002, "productName": "6x11 Greetings from Rostov-Na-Donu", "qty": 3, "totalAmount": 6.300000000000001, "salesChannel": "mobile app", "customer": {"firstname": "Mike", "lastname": "Jenkins", "email": "Mike.Jenkins@example.com"}, "dateCreated": "20191111", "seriesCity": "Rostov-Na-Donu", "Created Date": "2019-11-11", "transactionId": 20450}, {"date": "20191111", "reseller-id": 1002, "productName": "4.25x6 All the love from Kobenhavn (Copenhagen)", "qty": 2, "totalAmount": 7.6, "salesChannel": "web", "customer": {"firstname": "Ayesha", "lastname": "Armstrong", "email": "Ayesha.Armstrong@example.com"}, "dateCreated": "20191111", "seriesCity": "Kobenhavn (Copenhagen)", "Created Date": "2019-11-11", "transactionId": 20451}, {"date": "20191111", "reseller-id": 1002, "productName": "6x11 Merry Christmas from Odessa", "qty": 6, "totalAmount": 15.0, "salesChannel": "web", "customer": {"firstname": "Diane", "lastname": "Cooper", "email": "Diane.Cooper@example.com"}, "dateCreated": "20191111", "seriesCity": "Odessa", "Created Date": "2019-11-11", "transactionId": 20452}, {"date": "20191111", "reseller-id": 1002, "productName": "6x11 Just settled in Kishinev", "qty": 5, "totalAmount": 17.0, "salesChannel": "web", "customer": {"firstname": "Antonia", "lastname": "Burnett", "email": "Antonia.Burnett@example.com"}, "dateCreated": "20191111", "seriesCity": "Kishinev", "Created Date": "2019-11-11", "transactionId": 20453}, {"date": "20191111", "reseller-id": 1002, "productName": "4.25x6 Come visit me in Naberezhnye Tchelny", "qty": 3, "totalAmount": 7.5, "salesChannel": "web", "customer": {"firstname": "Alice", "lastname": "Martin", "email": "Alice.Martin@example.com"}, "dateCreated": "20191111", "seriesCity": "Naberezhnye Tchelny", "Created Date": "2019-11-11", "transactionId": 20454}, {"date": "20191111", "reseller-id": 1002, "productName": "6x11 Merry Christmas from Essen", "qty": 1, "totalAmount": 2.6, "salesChannel": "mobile app", "customer": {"firstname": "Stella", "lastname": "Robichaux", "email": "Stella.Robichaux@example.com"}, "dateCreated": "20191111", "seriesCity": "Essen", "Created Date": "2019-11-11", "transactionId": 20455}, {"date": "20191111", "reseller-id": 1002, "productName": "4.25x6 Merry Christmas from Ryazan", "qty": 6, "totalAmount": 24.0, "salesChannel": "mobile app", "customer": {"firstname": "Alice", "lastname": "Mcgill", "email": "Alice.Mcgill@example.com"}, "dateCreated": "20191111", "seriesCity": "Ryazan", "Created Date": "2019-11-11", "transactionId": 20456}, {"date": "20191111", "reseller-id": 1002, "productName": "5x7 Merry Christmas from Ekaterinoburg", "qty": 1, "totalAmount": 1.7, "salesChannel": "mobile app", "customer": {"firstname": "Linda", "lastname": "Davis", "email": "Linda.Davis@example.com"}, "dateCreated": "20191111", "seriesCity": "Ekaterinoburg", "Created Date": "2019-11-11", "transactionId": 20457}, {"date": "20191111", "reseller-id": 1002, "productName": "5.5x8.5 Just settled in Madrid", "qty": 3, "totalAmount": 9.3, "salesChannel": "mobile app", "customer": {"firstname": "Rosa", "lastname": "Hill", "email": "Rosa.Hill@example.com"}, "dateCreated": "20191111", "seriesCity": "Madrid", "Created Date": "2019-11-11", "transactionId": 20458}, {"date": "20191111", "reseller-id": 1002, "productName": "4.25x6 Greetings from Budapest", "qty": 2, "totalAmount": 7.8, "salesChannel": "mobile app", "customer": {"firstname": "Byron", "lastname": "Williams", "email": "Byron.Williams@example.com"}, "dateCreated": "20191111", "seriesCity": "Budapest", "Created Date": "2019-11-11", "transactionId": 20459}, {"date": "20191111", "reseller-id": 1002, "productName": "6x11 Greetings from Valencia", "qty": 2, "totalAmount": 3.2, "salesChannel": "web", "customer": {"firstname": "David", "lastname": "Batun", "email": "David.Batun@example.com"}, "dateCreated": "20191111", "seriesCity": "Valencia", "Created Date": "2019-11-11", "transactionId": 20460}, {"date": "20191111", "reseller-id": 1002, "productName": "5x7 Greetings from Lvov", "qty": 1, "totalAmount": 4.3, "salesChannel": "web", "customer": {"firstname": "Teri", "lastname": "Garcia", "email": "Teri.Garcia@example.com"}, "dateCreated": "20191111", "seriesCity": "Lvov", "Created Date": "2019-11-11", "transactionId": 20461}, {"date": "20191111", "reseller-id": 1002, "productName": "5x7 All the love from Lipetsk", "qty": 5, "totalAmount": 13.5, "salesChannel": "mobile app", "customer": {"firstname": "Juan", "lastname": "Carter", "email": "Juan.Carter@example.com"}, "dateCreated": "20191111", "seriesCity": "Lipetsk", "Created Date": "2019-11-11", "transactionId": 20462}, {"date": "20191111", "reseller-id": 1002, "productName": "4x6 Greetings from Voronezh", "qty": 6, "totalAmount": 10.2, "salesChannel": "mobile app", "customer": {"firstname": "Mark", "lastname": "Scofield", "email": "Mark.Scofield@example.com"}, "dateCreated": "20191111", "seriesCity": "Voronezh", "Created Date": "2019-11-11", "transactionId": 20463}, {"date": "20191111", "reseller-id": 1002, "productName": "5x7 Merry Christmas from Kishinev", "qty": 5, "totalAmount": 11.0, "salesChannel": "mobile app", "customer": {"firstname": "Sofia", "lastname": "Zackery", "email": "Sofia.Zackery@example.com"}, "dateCreated": "20191111", "seriesCity": "Kishinev", "Created Date": "2019-11-11", "transactionId": 20464}, {"date": "20191111", "reseller-id": 1002, "productName": "5.5x8.5 Greetings from Zaragoza", "qty": 1, "totalAmount": 2.7, "salesChannel": "mobile app", "customer": {"firstname": "Tiffany", "lastname": "Prior", "email": "Tiffany.Prior@example.com"}, "dateCreated": "20191111", "seriesCity": "Zaragoza", "Created Date": "2019-11-11", "transactionId": 20465}, {"date": "20191111", "reseller-id": 1002, "productName": "5.5x8.5 Just settled in Izhevsk", "qty": 6, "totalAmount": 9.0, "salesChannel": "mobile app", "customer": {"firstname": "Anthony", "lastname": "James", "email": "Anthony.James@example.com"}, "dateCreated": "20191111", "seriesCity": "Izhevsk", "Created Date": "2019-11-11", "transactionId": 20466}, {"date": "20191111", "reseller-id": 1002, "productName": "4.25x6 Merry Christmas from Tolyatti", "qty": 4, "totalAmount": 10.0, "salesChannel": "web", "customer": {"firstname": "Sharon", "lastname": "Fossey", "email": "Sharon.Fossey@example.com"}, "dateCreated": "20191111", "seriesCity": "Tolyatti", "Created Date": "2019-11-11", "transactionId": 20467}, {"date": "20191111", "reseller-id": 1002, "productName": "5.5x8.5 Greetings from Zagreb", "qty": 4, "totalAmount": 14.8, "salesChannel": "mobile app", "customer": {"firstname": "Everette", "lastname": "Johnson", "email": "Everette.Johnson@example.com"}, "dateCreated": "20191111", "seriesCity": "Zagreb", "Created Date": "2019-11-11", "transactionId": 20468}, {"date": "20191111", "reseller-id": 1002, "productName": "4x6 Greetings from Duisburg", "qty": 6, "totalAmount": 23.4, "salesChannel": "mobile app", "customer": {"firstname": "Lloyd", "lastname": "Norman", "email": "Lloyd.Norman@example.com"}, "dateCreated": "20191111", "seriesCity": "Duisburg", "Created Date": "2019-11-11", "transactionId": 20469}, {"date": "20191111", "reseller-id": 1002, "productName": "4.25x6 Greetings from Vladivostok", "qty": 1, "totalAmount": 4.4, "salesChannel": "web", "customer": {"firstname": "Jess", "lastname": "Miranda", "email": "Jess.Miranda@example.com"}, "dateCreated": "20191111", "seriesCity": "Vladivostok", "Created Date": "2019-11-11", "transactionId": 20470}, {"date": "20191111", "reseller-id": 1002, "productName": "4.25x6 Greetings from Ufa", "qty": 5, "totalAmount": 19.0, "salesChannel": "mobile app", "customer": {"firstname": "Stacey", "lastname": "Preston", "email": "Stacey.Preston@example.com"}, "dateCreated": "20191111", "seriesCity": "Ufa", "Created Date": "2019-11-11", "transactionId": 20471}, {"date": "20191111", "reseller-id": 1002, "productName": "5x7 Greetings from Naberezhnye Tchelny", "qty": 4, "totalAmount": 7.2, "salesChannel": "mobile app", "customer": {"firstname": "Kathleen", "lastname": "Gunn", "email": "Kathleen.Gunn@example.com"}, "dateCreated": "20191111", "seriesCity": "Naberezhnye Tchelny", "Created Date": "2019-11-11", "transactionId": 20472}, {"date": "20191111", "reseller-id": 1002, "productName": "6x9 Just settled in Voronezh", "qty": 5, "totalAmount": 11.0, "salesChannel": "in-store", "customer": {"firstname": "Richard", "lastname": "Rothfeld", "email": "Richard.Rothfeld@example.com"}, "dateCreated": "20191111", "seriesCity": "Voronezh", "Created Date": "2019-11-11", "transactionId": 20473}, {"date": "20191111", "reseller-id": 1002, "productName": "5.5x8.5 Come visit me in Sheffield", "qty": 5, "totalAmount": 18.0, "salesChannel": "mobile app", "customer": {"firstname": "Lindsay", "lastname": "Younglas", "email": "Lindsay.Younglas@example.com"}, "dateCreated": "20191111", "seriesCity": "Sheffield", "Created Date": "2019-11-11", "transactionId": 20474}, {"date": "20191111", "reseller-id": 1002, "productName": "6x9 Just settled in Odessa", "qty": 1, "totalAmount": 1.7, "salesChannel": "in-store", "customer": {"firstname": "Angela", "lastname": "Biddle", "email": "Angela.Biddle@example.com"}, "dateCreated": "20191111", "seriesCity": "Odessa", "Created Date": "2019-11-11", "transactionId": 20475}, {"date": "20191111", "reseller-id": 1002, "productName": "5x7 Merry Christmas from Volgograd", "qty": 1, "totalAmount": 4.2, "salesChannel": "mobile app", "customer": {"firstname": "Fernando", "lastname": "Healy", "email": "Fernando.Healy@example.com"}, "dateCreated": "20191111", "seriesCity": "Volgograd", "Created Date": "2019-11-11", "transactionId": 20476}, {"date": "20191111", "reseller-id": 1002, "productName": "6x9 Merry Christmas from Glasgow", "qty": 2, "totalAmount": 4.0, "salesChannel": "mobile app", "customer": {"firstname": "Sandra", "lastname": "Boothroyd", "email": "Sandra.Boothroyd@example.com"}, "dateCreated": "20191111", "seriesCity": "Glasgow", "Created Date": "2019-11-11", "transactionId": 20477}, {"date": "20191111", "reseller-id": 1002, "productName": "4.25x6 All the love from Sevilla", "qty": 3, "totalAmount": 5.4, "salesChannel": "web", "customer": {"firstname": "John", "lastname": "Hamilton", "email": "John.Hamilton@example.com"}, "dateCreated": "20191111", "seriesCity": "Sevilla", "Created Date": "2019-11-11", "transactionId": 20478}]